Bard.py
GoogleBard-2.1.0.dist-info/LICENSE
GoogleBard-2.1.0.dist-info/METADATA
GoogleBard-2.1.0.dist-info/WHEEL
GoogleBard-2.1.0.dist-info/top_level.txt
GoogleBard-2.1.0.dist-info/RECORD
